{
  "('dj', 4, 'aer_simulator')": 50,
  "('dj', 4, 'fake_kyiv')": 50,
  "('dj', 4, 'fake_marrakesh')": 50,
  "('dj', 4, 'fake_sherbrooke')": 50,
  "('dj', 5, 'aer_simulator')": 50,
  "('dj', 5, 'fake_fez')": 50,
  "('dj', 5, 'fake_kyiv')": 50,
  "('dj', 5, 'fake_marrakesh')": 50,
  "('dj', 5, 'fake_sherbrooke')": 50,
  "('dj', 5, 'fake_torino')": 50,
  "('dj', 6, 'aer_simulator')": 50,
  "('dj', 6, 'fake_fez')": 50,
  "('dj', 6, 'fake_kyiv')": 50,
  "('dj', 6, 'fake_marrakesh')": 50,
  "('dj', 6, 'fake_sherbrooke')": 50,
  "('dj', 6, 'fake_torino')": 100,
  "('dj', 7, 'aer_simulator')": 50,
  "('dj', 7, 'fake_fez')": 50,
  "('dj', 7, 'fake_kyiv')": 100,
  "('dj', 7, 'fake_marrakesh')": 50,
  "('dj', 7, 'fake_sherbrooke')": 150,
  "('dj', 7, 'fake_torino')": 200,
  "('dj', 8, 'aer_simulator')": 50,
  "('dj', 8, 'fake_kyiv')": 150,
  "('dj', 8, 'fake_sherbrooke')": 150,
  "('dj', 8, 'fake_torino')": 250,
  "('dj', 9, 'aer_simulator')": 50,
  "('dj', 9, 'fake_fez')": 50,
  "('dj', 9, 'fake_kyiv')": 200,
  "('dj', 9, 'fake_marrakesh')": 200,
  "('dj', 9, 'fake_sherbrooke')": 250,
  "('dj', 9, 'fake_torino')": 400,
  "('dj', 10, 'aer_simulator')": 50,
  "('dj', 10, 'fake_kyiv')": 500,
  "('dj', 10, 'fake_marrakesh')": 150,
  "('dj', 10, 'fake_sherbrooke')": 400,
  "('dj', 11, 'aer_simulator')": 50,
  "('dj', 11, 'fake_fez')": 200,
  "('dj', 11, 'fake_kyiv')": 800,
  "('dj', 11, 'fake_marrakesh')": 200,
  "('dj', 11, 'fake_sherbrooke')": 600,
  "('dj', 11, 'fake_torino')": 500,
  "('dj', 12, 'aer_simulator')": 50,
  "('dj', 12, 'fake_fez')": 200,
  "('dj', 12, 'fake_kyiv')": 750,
  "('dj', 12, 'fake_marrakesh')": 100,
  "('dj', 12, 'fake_sherbrooke')": 900,
  "('dj', 12, 'fake_torino')": 500,
  "('dj', 13, 'aer_simulator')": 50,
  "('dj', 13, 'fake_fez')": 250,
  "('dj', 13, 'fake_kyiv')": 700,
  "('dj', 13, 'fake_marrakesh')": 200,
  "('dj', 13, 'fake_sherbrooke')": 800,
  "('dj', 13, 'fake_torino')": 650,
  "('dj', 14, 'aer_simulator')": 50,
  "('dj', 14, 'fake_kyiv')": 1800,
  "('dj', 14, 'fake_sherbrooke')": 750,
  "('dj', 14, 'fake_torino')": 1100,
  "('dj', 15, 'aer_simulator')": 50,
  "('dj', 15, 'fake_fez')": 650,
  "('dj', 15, 'fake_kyiv')": 2500,
  "('dj', 15, 'fake_marrakesh')": 400,
  "('dj', 15, 'fake_sherbrooke')": 1700,
  "('dj', 15, 'fake_torino')": 1900,
  "('ghz', 4, 'aer_simulator')": 100,
  "('ghz', 4, 'fake_fez')": 50,
  "('ghz', 4, 'fake_kyiv')": 100,
  "('ghz', 4, 'fake_marrakesh')": 150,
  "('ghz', 4, 'fake_sherbrooke')": 50,
  "('ghz', 4, 'fake_torino')": 100,
  "('ghz', 5, 'aer_simulator')": 100,
  "('ghz', 5, 'fake_fez')": 50,
  "('ghz', 5, 'fake_kyiv')": 200,
  "('ghz', 5, 'fake_marrakesh')": 50,
  "('ghz', 5, 'fake_sherbrooke')": 50,
  "('ghz', 5, 'fake_torino')": 100,
  "('ghz', 6, 'aer_simulator')": 50,
  "('ghz', 6, 'fake_fez')": 150,
  "('ghz', 6, 'fake_kyiv')": 100,
  "('ghz', 6, 'fake_marrakesh')": 200,
  "('ghz', 6, 'fake_sherbrooke')": 100,
  "('ghz', 6, 'fake_torino')": 100,
  "('ghz', 7, 'aer_simulator')": 50,
  "('ghz', 7, 'fake_fez')": 250,
  "('ghz', 7, 'fake_kyiv')": 50,
  "('ghz', 7, 'fake_marrakesh')": 50,
  "('ghz', 7, 'fake_sherbrooke')": 50,
  "('ghz', 7, 'fake_torino')": 50,
  "('ghz', 8, 'aer_simulator')": 50,
  "('ghz', 8, 'fake_fez')": 150,
  "('ghz', 8, 'fake_kyiv')": 100,
  "('ghz', 8, 'fake_marrakesh')": 100,
  "('ghz', 8, 'fake_sherbrooke')": 250,
  "('ghz', 8, 'fake_torino')": 250,
  "('ghz', 9, 'aer_simulator')": 50,
  "('ghz', 9, 'fake_fez')": 100,
  "('ghz', 9, 'fake_kyiv')": 150,
  "('ghz', 9, 'fake_marrakesh')": 150,
  "('ghz', 9, 'fake_sherbrooke')": 100,
  "('ghz', 9, 'fake_torino')": 250,
  "('ghz', 10, 'aer_simulator')": 50,
  "('ghz', 10, 'fake_fez')": 50,
  "('ghz', 10, 'fake_kyiv')": 150,
  "('ghz', 10, 'fake_marrakesh')": 150,
  "('ghz', 10, 'fake_sherbrooke')": 300,
  "('ghz', 10, 'fake_torino')": 250,
  "('ghz', 11, 'aer_simulator')": 50,
  "('ghz', 11, 'fake_fez')": 300,
  "('ghz', 11, 'fake_kyiv')": 200,
  "('ghz', 11, 'fake_marrakesh')": 100,
  "('ghz', 11, 'fake_sherbrooke')": 250,
  "('ghz', 11, 'fake_torino')": 250,
  "('ghz', 12, 'aer_simulator')": 200,
  "('ghz', 12, 'fake_fez')": 350,
  "('ghz', 12, 'fake_kyiv')": 500,
  "('ghz', 12, 'fake_marrakesh')": 50,
  "('ghz', 12, 'fake_sherbrooke')": 200,
  "('ghz', 12, 'fake_torino')": 300,
  "('ghz', 13, 'aer_simulator')": 50,
  "('ghz', 13, 'fake_fez')": 200,
  "('ghz', 13, 'fake_kyiv')": 500,
  "('ghz', 13, 'fake_marrakesh')": 50,
  "('ghz', 13, 'fake_sherbrooke')": 600,
  "('ghz', 13, 'fake_torino')": 900,
  "('ghz', 14, 'aer_simulator')": 50,
  "('ghz', 14, 'fake_fez')": 250,
  "('ghz', 14, 'fake_kyiv')": 750,
  "('ghz', 14, 'fake_marrakesh')": 150,
  "('ghz', 14, 'fake_sherbrooke')": 750,
  "('ghz', 14, 'fake_torino')": 1200,
  "('ghz', 15, 'aer_simulator')": 50,
  "('ghz', 15, 'fake_fez')": 600,
  "('ghz', 15, 'fake_kyiv')": 600,
  "('ghz', 15, 'fake_marrakesh')": 250,
  "('ghz', 15, 'fake_sherbrooke')": 500,
  "('ghz', 15, 'fake_torino')": 550,
  "('qaoa', 4, 'aer_simulator')": 100,
  "('qaoa', 4, 'fake_fez')": 50,
  "('qaoa', 4, 'fake_kyiv')": 100,
  "('qaoa', 4, 'fake_marrakesh')": 100,
  "('qaoa', 4, 'fake_torino')": 100,
  "('qaoa', 5, 'aer_simulator')": 200,
  "('qaoa', 5, 'fake_fez')": 250,
  "('qaoa', 5, 'fake_kyiv')": 450,
  "('qaoa', 5, 'fake_marrakesh')": 150,
  "('qaoa', 5, 'fake_sherbrooke')": 500,
  "('qaoa', 5, 'fake_torino')": 300,
  "('qaoa', 6, 'aer_simulator')": 350,
  "('qaoa', 6, 'fake_fez')": 650,
  "('qaoa', 6, 'fake_kyiv')": 600,
  "('qaoa', 6, 'fake_sherbrooke')": 650,
  "('qaoa', 6, 'fake_torino')": 700,
  "('qaoa', 7, 'aer_simulator')": 1000,
  "('qaoa', 7, 'fake_fez')": 1050,
  "('qaoa', 7, 'fake_kyiv')": 1350,
  "('qaoa', 7, 'fake_marrakesh')": 1000,
  "('qaoa', 7, 'fake_sherbrooke')": 1500,
  "('qaoa', 7, 'fake_torino')": 1150,
  "('qaoa', 8, 'aer_simulator')": 1150,
  "('qaoa', 8, 'fake_fez')": 1850,
  "('qaoa', 8, 'fake_marrakesh')": 1400,
  "('qaoa', 8, 'fake_torino')": 1900,
  "('qaoa', 9, 'aer_simulator')": 1100,
  "('qaoa', 9, 'fake_fez')": 3000,
  "('qaoa', 9, 'fake_kyiv')": 3550,
  "('qaoa', 9, 'fake_marrakesh')": 2250,
  "('qaoa', 9, 'fake_sherbrooke')": 3350,
  "('qaoa', 9, 'fake_torino')": 3100,
  "('qaoa', 10, 'aer_simulator')": 2400,
  "('qaoa', 10, 'fake_fez')": 4750,
  "('qaoa', 10, 'fake_kyiv')": 6100,
  "('qaoa', 10, 'fake_marrakesh')": 5100,
  "('qaoa', 10, 'fake_torino')": 5700,
  "('qaoa', 11, 'aer_simulator')": 3600,
  "('qaoa', 11, 'fake_fez')": 5600,
  "('qaoa', 11, 'fake_kyiv')": 7500,
  "('qaoa', 11, 'fake_marrakesh')": 5050,
  "('qaoa', 11, 'fake_sherbrooke')": 6900,
  "('qaoa', 11, 'fake_torino')": 7200,
  "('qaoa', 12, 'aer_simulator')": 4600,
  "('qaoa', 12, 'fake_fez')": 7550,
  "('qaoa', 12, 'fake_kyiv')": 10300,
  "('qaoa', 12, 'fake_sherbrooke')": 9850,
  "('qaoa', 12, 'fake_torino')": 9350,
  "('qaoa', 13, 'aer_simulator')": 6350,
  "('qaoa', 13, 'fake_fez')": 10450,
  "('qaoa', 13, 'fake_kyiv')": 13100,
  "('qaoa', 13, 'fake_marrakesh')": 10450,
  "('qaoa', 13, 'fake_sherbrooke')": 12350,
  "('qaoa', 13, 'fake_torino')": 12150,
  "('qaoa', 14, 'aer_simulator')": 3250,
  "('qaoa', 14, 'fake_fez')": 9000,
  "('qaoa', 14, 'fake_marrakesh')": 8650,
  "('qaoa', 14, 'fake_torino')": 11850,
  "('qaoa', 15, 'aer_simulator')": 10200,
  "('qaoa', 15, 'fake_fez')": 14200,
  "('qaoa', 15, 'fake_kyiv')": 15950,
  "('qaoa', 15, 'fake_marrakesh')": 13500,
  "('qaoa', 15, 'fake_sherbrooke')": 15500,
  "('qaoa', 15, 'fake_torino')": 15250,
  "('qft', 4, 'aer_simulator')": 500,
  "('qft', 4, 'fake_fez')": 250,
  "('qft', 4, 'fake_kyiv')": 350,
  "('qft', 4, 'fake_marrakesh')": 250,
  "('qft', 4, 'fake_sherbrooke')": 150,
  "('qft', 4, 'fake_torino')": 250,
  "('qft', 5, 'aer_simulator')": 550,
  "('qft', 5, 'fake_fez')": 600,
  "('qft', 5, 'fake_kyiv')": 600,
  "('qft', 5, 'fake_marrakesh')": 500,
  "('qft', 5, 'fake_sherbrooke')": 550,
  "('qft', 5, 'fake_torino')": 450,
  "('qft', 6, 'aer_simulator')": 1200,
  "('qft', 6, 'fake_kyiv')": 850,
  "('qft', 6, 'fake_marrakesh')": 950,
  "('qft', 6, 'fake_sherbrooke')": 1000,
  "('qft', 7, 'aer_simulator')": 2200,
  "('qft', 7, 'fake_fez')": 1450,
  "('qft', 7, 'fake_kyiv')": 2200,
  "('qft', 7, 'fake_marrakesh')": 1750,
  "('qft', 7, 'fake_sherbrooke')": 1800,
  "('qft', 7, 'fake_torino')": 2350,
  "('qft', 8, 'aer_simulator')": 3600,
  "('qft', 8, 'fake_kyiv')": 3250,
  "('qft', 8, 'fake_marrakesh')": 3500,
  "('qft', 8, 'fake_sherbrooke')": 3200,
  "('qft', 9, 'aer_simulator')": 5300,
  "('qft', 9, 'fake_fez')": 5900,
  "('qft', 9, 'fake_kyiv')": 6200,
  "('qft', 9, 'fake_marrakesh')": 6000,
  "('qft', 9, 'fake_sherbrooke')": 6100,
  "('qft', 9, 'fake_torino')": 6250,
  "('qft', 10, 'aer_simulator')": 8750,
  "('qft', 10, 'fake_fez')": 9050,
  "('qft', 10, 'fake_kyiv')": 8700,
  "('qft', 10, 'fake_marrakesh')": 8950,
  "('qft', 10, 'fake_sherbrooke')": 8900,
  "('qft', 10, 'fake_torino')": 8800,
  "('qft', 11, 'aer_simulator')": 12600,
  "('qft', 11, 'fake_fez')": 12300,
  "('qft', 11, 'fake_kyiv')": 12500,
  "('qft', 11, 'fake_marrakesh')": 12400,
  "('qft', 11, 'fake_sherbrooke')": 12400,
  "('qft', 11, 'fake_torino')": 12350,
  "('qft', 12, 'aer_simulator')": 15100,
  "('qft', 12, 'fake_kyiv')": 15350,
  "('qft', 12, 'fake_marrakesh')": 15400,
  "('qft', 12, 'fake_sherbrooke')": 15250,
  "('qft', 13, 'aer_simulator')": 17200,
  "('qft', 13, 'fake_fez')": 17200,
  "('qft', 13, 'fake_kyiv')": 17200,
  "('qft', 13, 'fake_marrakesh')": 17200,
  "('qft', 13, 'fake_sherbrooke')": 17200,
  "('qft', 13, 'fake_torino')": 17200,
  "('qft', 14, 'aer_simulator')": 17750,
  "('qft', 14, 'fake_kyiv')": 17750,
  "('qft', 14, 'fake_marrakesh')": 17750,
  "('qft', 14, 'fake_sherbrooke')": 17700,
  "('qft', 15, 'aer_simulator')": 17900,
  "('qft', 15, 'fake_fez')": 17900,
  "('qft', 15, 'fake_kyiv')": 17900,
  "('qft', 15, 'fake_marrakesh')": 17900,
  "('qft', 15, 'fake_sherbrooke')": 17900,
  "('qft', 15, 'fake_torino')": 17900,
  "('qnn', 4, 'aer_simulator')": 250,
  "('qnn', 4, 'fake_fez')": 200,
  "('qnn', 4, 'fake_kyiv')": 150,
  "('qnn', 4, 'fake_marrakesh')": 150,
  "('qnn', 4, 'fake_sherbrooke')": 500,
  "('qnn', 4, 'fake_torino')": 150,
  "('qnn', 5, 'aer_simulator')": 300,
  "('qnn', 5, 'fake_fez')": 250,
  "('qnn', 5, 'fake_kyiv')": 400,
  "('qnn', 5, 'fake_marrakesh')": 350,
  "('qnn', 5, 'fake_sherbrooke')": 650,
  "('qnn', 5, 'fake_torino')": 350,
  "('qnn', 6, 'aer_simulator')": 450,
  "('qnn', 6, 'fake_fez')": 650,
  "('qnn', 6, 'fake_kyiv')": 700,
  "('qnn', 6, 'fake_marrakesh')": 550,
  "('qnn', 6, 'fake_sherbrooke')": 550,
  "('qnn', 6, 'fake_torino')": 1200,
  "('qnn', 7, 'aer_simulator')": 1550,
  "('qnn', 7, 'fake_fez')": 1750,
  "('qnn', 7, 'fake_kyiv')": 1650,
  "('qnn', 7, 'fake_marrakesh')": 1550,
  "('qnn', 7, 'fake_sherbrooke')": 2000,
  "('qnn', 7, 'fake_torino')": 1700,
  "('qnn', 8, 'aer_simulator')": 1950,
  "('qnn', 8, 'fake_marrakesh')": 2400,
  "('qnn', 8, 'fake_sherbrooke')": 2700,
  "('qnn', 8, 'fake_torino')": 2800,
  "('qnn', 9, 'aer_simulator')": 3800,
  "('qnn', 9, 'fake_fez')": 5100,
  "('qnn', 9, 'fake_kyiv')": 5050,
  "('qnn', 9, 'fake_marrakesh')": 4800,
  "('qnn', 9, 'fake_sherbrooke')": 5750,
  "('qnn', 9, 'fake_torino')": 5250,
  "('qnn', 10, 'aer_simulator')": 6600,
  "('qnn', 10, 'fake_fez')": 8350,
  "('qnn', 10, 'fake_kyiv')": 8900,
  "('qnn', 10, 'fake_marrakesh')": 7950,
  "('qnn', 10, 'fake_sherbrooke')": 8450,
  "('qnn', 10, 'fake_torino')": 8400,
  "('qnn', 11, 'aer_simulator')": 9250,
  "('qnn', 11, 'fake_fez')": 12100,
  "('qnn', 11, 'fake_kyiv')": 12300,
  "('qnn', 11, 'fake_marrakesh')": 11300,
  "('qnn', 11, 'fake_sherbrooke')": 12150,
  "('qnn', 11, 'fake_torino')": 11850,
  "('qnn', 12, 'aer_simulator')": 11300,
  "('qnn', 12, 'fake_fez')": 14700,
  "('qnn', 12, 'fake_kyiv')": 15000,
  "('qnn', 12, 'fake_marrakesh')": 14350,
  "('qnn', 12, 'fake_sherbrooke')": 14950,
  "('qnn', 12, 'fake_torino')": 14900,
  "('qnn', 13, 'aer_simulator')": 14400,
  "('qnn', 13, 'fake_fez')": 16900,
  "('qnn', 13, 'fake_kyiv')": 17150,
  "('qnn', 13, 'fake_marrakesh')": 16650,
  "('qnn', 13, 'fake_sherbrooke')": 17100,
  "('qnn', 13, 'fake_torino')": 16950,
  "('qnn', 14, 'aer_simulator')": 16250,
  "('qnn', 14, 'fake_marrakesh')": 17450,
  "('qnn', 14, 'fake_sherbrooke')": 17700,
  "('qnn', 14, 'fake_torino')": 17650,
  "('qnn', 15, 'aer_simulator')": 16500,
  "('qnn', 15, 'fake_fez')": 17800,
  "('qnn', 15, 'fake_kyiv')": 17900,
  "('qnn', 15, 'fake_marrakesh')": 17700,
  "('qnn', 15, 'fake_sherbrooke')": 17900,
  "('qnn', 15, 'fake_torino')": 17850,
  "('qpeexact', 4, 'aer_simulator')": 50,
  "('qpeexact', 4, 'fake_fez')": 50,
  "('qpeexact', 4, 'fake_kyiv')": 50,
  "('qpeexact', 4, 'fake_marrakesh')": 50,
  "('qpeexact', 4, 'fake_sherbrooke')": 50,
  "('qpeexact', 4, 'fake_torino')": 50,
  "('qpeexact', 5, 'aer_simulator')": 50,
  "('qpeexact', 5, 'fake_fez')": 50,
  "('qpeexact', 5, 'fake_kyiv')": 50,
  "('qpeexact', 5, 'fake_marrakesh')": 50,
  "('qpeexact', 5, 'fake_sherbrooke')": 100,
  "('qpeexact', 5, 'fake_torino')": 50,
  "('qpeexact', 6, 'aer_simulator')": 50,
  "('qpeexact', 6, 'fake_fez')": 100,
  "('qpeexact', 6, 'fake_kyiv')": 200,
  "('qpeexact', 6, 'fake_marrakesh')": 50,
  "('qpeexact', 6, 'fake_sherbrooke')": 200,
  "('qpeexact', 6, 'fake_torino')": 100,
  "('qpeexact', 7, 'aer_simulator')": 50,
  "('qpeexact', 7, 'fake_fez')": 150,
  "('qpeexact', 7, 'fake_kyiv')": 350,
  "('qpeexact', 7, 'fake_marrakesh')": 100,
  "('qpeexact', 7, 'fake_sherbrooke')": 300,
  "('qpeexact', 7, 'fake_torino')": 350,
  "('qpeexact', 8, 'aer_simulator')": 50,
  "('qpeexact', 8, 'fake_fez')": 300,
  "('qpeexact', 8, 'fake_kyiv')": 600,
  "('qpeexact', 8, 'fake_marrakesh')": 200,
  "('qpeexact', 8, 'fake_sherbrooke')": 900,
  "('qpeexact', 8, 'fake_torino')": 300,
  "('qpeexact', 9, 'aer_simulator')": 50,
  "('qpeexact', 9, 'fake_fez')": 750,
  "('qpeexact', 9, 'fake_kyiv')": 2050,
  "('qpeexact', 9, 'fake_marrakesh')": 500,
  "('qpeexact', 9, 'fake_sherbrooke')": 1450,
  "('qpeexact', 9, 'fake_torino')": 950,
  "('qpeexact', 10, 'aer_simulator')": 50,
  "('qpeexact', 10, 'fake_fez')": 1100,
  "('qpeexact', 10, 'fake_kyiv')": 2800,
  "('qpeexact', 10, 'fake_marrakesh')": 700,
  "('qpeexact', 10, 'fake_sherbrooke')": 2550,
  "('qpeexact', 10, 'fake_torino')": 1950,
  "('qpeexact', 11, 'aer_simulator')": 50,
  "('qpeexact', 11, 'fake_fez')": 2250,
  "('qpeexact', 11, 'fake_kyiv')": 5650,
  "('qpeexact', 11, 'fake_marrakesh')": 2100,
  "('qpeexact', 11, 'fake_sherbrooke')": 4950,
  "('qpeexact', 11, 'fake_torino')": 3000,
  "('qpeexact', 12, 'aer_simulator')": 50,
  "('qpeexact', 12, 'fake_fez')": 3450,
  "('qpeexact', 12, 'fake_kyiv')": 8700,
  "('qpeexact', 12, 'fake_marrakesh')": 2950,
  "('qpeexact', 12, 'fake_sherbrooke')": 7500,
  "('qpeexact', 12, 'fake_torino')": 5350,
  "('qpeexact', 13, 'aer_simulator')": 50,
  "('qpeexact', 13, 'fake_fez')": 5500,
  "('qpeexact', 13, 'fake_kyiv')": 12250,
  "('qpeexact', 13, 'fake_marrakesh')": 4600,
  "('qpeexact', 13, 'fake_sherbrooke')": 10800,
  "('qpeexact', 13, 'fake_torino')": 8650,
  "('qpeexact', 14, 'aer_simulator')": 50,
  "('qpeexact', 14, 'fake_fez')": 8600,
  "('qpeexact', 14, 'fake_kyiv')": 14850,
  "('qpeexact', 14, 'fake_marrakesh')": 7050,
  "('qpeexact', 14, 'fake_sherbrooke')": 13550,
  "('qpeexact', 14, 'fake_torino')": 11000,
  "('qpeexact', 15, 'aer_simulator')": 50,
  "('qpeexact', 15, 'fake_fez')": 11100,
  "('qpeexact', 15, 'fake_kyiv')": 16550,
  "('qpeexact', 15, 'fake_marrakesh')": 9400,
  "('qpeexact', 15, 'fake_sherbrooke')": 15700,
  "('qpeexact', 15, 'fake_torino')": 13650,
  "('random', 4, 'aer_simulator')": 50,
  "('random', 4, 'fake_fez')": 200,
  "('random', 4, 'fake_kyiv')": 100,
  "('random', 4, 'fake_marrakesh')": 250,
  "('random', 4, 'fake_sherbrooke')": 150,
  "('random', 4, 'fake_torino')": 250,
  "('random', 5, 'aer_simulator')": 100,
  "('random', 5, 'fake_fez')": 350,
  "('random', 5, 'fake_kyiv')": 350,
  "('random', 5, 'fake_marrakesh')": 250,
  "('random', 5, 'fake_sherbrooke')": 700,
  "('random', 5, 'fake_torino')": 200,
  "('random', 6, 'aer_simulator')": 300,
  "('random', 6, 'fake_kyiv')": 850,
  "('random', 6, 'fake_marrakesh')": 550,
  "('random', 6, 'fake_sherbrooke')": 1000,
  "('random', 6, 'fake_torino')": 650,
  "('random', 7, 'aer_simulator')": 200,
  "('random', 7, 'fake_fez')": 1400,
  "('random', 7, 'fake_kyiv')": 1750,
  "('random', 7, 'fake_marrakesh')": 1250,
  "('random', 7, 'fake_sherbrooke')": 1650,
  "('random', 7, 'fake_torino')": 1700,
  "('random', 8, 'aer_simulator')": 250,
  "('random', 8, 'fake_kyiv')": 3500,
  "('random', 8, 'fake_marrakesh')": 2500,
  "('random', 8, 'fake_sherbrooke')": 3400,
  "('random', 8, 'fake_torino')": 2950,
  "('random', 9, 'aer_simulator')": 450,
  "('random', 9, 'fake_fez')": 4750,
  "('random', 9, 'fake_kyiv')": 5850,
  "('random', 9, 'fake_marrakesh')": 4050,
  "('random', 9, 'fake_sherbrooke')": 5500,
  "('random', 9, 'fake_torino')": 5250,
  "('random', 10, 'aer_simulator')": 650,
  "('random', 10, 'fake_fez')": 8200,
  "('random', 10, 'fake_kyiv')": 8750,
  "('random', 10, 'fake_marrakesh')": 7600,
  "('random', 10, 'fake_sherbrooke')": 8750,
  "('random', 10, 'fake_torino')": 8550,
  "('random', 11, 'aer_simulator')": 7850,
  "('random', 11, 'fake_fez')": 12150,
  "('random', 11, 'fake_kyiv')": 12250,
  "('random', 11, 'fake_marrakesh')": 12450,
  "('random', 11, 'fake_sherbrooke')": 12600,
  "('random', 11, 'fake_torino')": 12300,
  "('random', 12, 'aer_simulator')": 10950,
  "('random', 12, 'fake_kyiv')": 15250,
  "('random', 12, 'fake_marrakesh')": 15000,
  "('random', 12, 'fake_sherbrooke')": 15250,
  "('random', 12, 'fake_torino')": 15300,
  "('random', 13, 'aer_simulator')": 12750,
  "('random', 13, 'fake_fez')": 17000,
  "('random', 13, 'fake_kyiv')": 17250,
  "('random', 13, 'fake_marrakesh')": 16900,
  "('random', 13, 'fake_sherbrooke')": 17200,
  "('random', 13, 'fake_torino')": 17150,
  "('random', 14, 'aer_simulator')": 10900,
  "('random', 14, 'fake_kyiv')": 17750,
  "('random', 14, 'fake_marrakesh')": 17650,
  "('random', 14, 'fake_sherbrooke')": 17700,
  "('random', 14, 'fake_torino')": 17750,
  "('random', 15, 'aer_simulator')": 16900,
  "('random', 15, 'fake_fez')": 17900,
  "('random', 15, 'fake_kyiv')": 17900,
  "('random', 15, 'fake_marrakesh')": 17850,
  "('random', 15, 'fake_sherbrooke')": 17900,
  "('random', 15, 'fake_torino')": 17900,
  "('realamprandom', 4, 'aer_simulator')": 100,
  "('realamprandom', 4, 'fake_fez')": 150,
  "('realamprandom', 4, 'fake_kyiv')": 200,
  "('realamprandom', 4, 'fake_marrakesh')": 100,
  "('realamprandom', 4, 'fake_sherbrooke')": 100,
  "('realamprandom', 4, 'fake_torino')": 150,
  "('realamprandom', 5, 'aer_simulator')": 350,
  "('realamprandom', 5, 'fake_fez')": 350,
  "('realamprandom', 5, 'fake_kyiv')": 450,
  "('realamprandom', 5, 'fake_marrakesh')": 500,
  "('realamprandom', 5, 'fake_sherbrooke')": 450,
  "('realamprandom', 5, 'fake_torino')": 500,
  "('realamprandom', 6, 'aer_simulator')": 600,
  "('realamprandom', 6, 'fake_fez')": 1000,
  "('realamprandom', 6, 'fake_kyiv')": 1000,
  "('realamprandom', 6, 'fake_marrakesh')": 950,
  "('realamprandom', 6, 'fake_sherbrooke')": 850,
  "('realamprandom', 6, 'fake_torino')": 1200,
  "('realamprandom', 7, 'aer_simulator')": 1100,
  "('realamprandom', 7, 'fake_fez')": 1350,
  "('realamprandom', 7, 'fake_kyiv')": 1750,
  "('realamprandom', 7, 'fake_marrakesh')": 1350,
  "('realamprandom', 7, 'fake_sherbrooke')": 1700,
  "('realamprandom', 7, 'fake_torino')": 1550,
  "('realamprandom', 8, 'aer_simulator')": 1800,
  "('realamprandom', 8, 'fake_fez')": 2450,
  "('realamprandom', 8, 'fake_kyiv')": 3100,
  "('realamprandom', 8, 'fake_marrakesh')": 2950,
  "('realamprandom', 8, 'fake_sherbrooke')": 3350,
  "('realamprandom', 8, 'fake_torino')": 3100,
  "('realamprandom', 9, 'aer_simulator')": 3000,
  "('realamprandom', 9, 'fake_fez')": 5350,
  "('realamprandom', 9, 'fake_kyiv')": 5550,
  "('realamprandom', 9, 'fake_marrakesh')": 4900,
  "('realamprandom', 9, 'fake_sherbrooke')": 6200,
  "('realamprandom', 9, 'fake_torino')": 5450,
  "('realamprandom', 10, 'aer_simulator')": 4950,
  "('realamprandom', 10, 'fake_fez')": 8850,
  "('realamprandom', 10, 'fake_kyiv')": 9000,
  "('realamprandom', 10, 'fake_marrakesh')": 8200,
  "('realamprandom', 10, 'fake_sherbrooke')": 9150,
  "('realamprandom', 10, 'fake_torino')": 8800,
  "('realamprandom', 11, 'aer_simulator')": 4950,
  "('realamprandom', 11, 'fake_fez')": 11550,
  "('realamprandom', 11, 'fake_kyiv')": 12550,
  "('realamprandom', 11, 'fake_marrakesh')": 11500,
  "('realamprandom', 11, 'fake_sherbrooke')": 11950,
  "('realamprandom', 11, 'fake_torino')": 12200,
  "('realamprandom', 12, 'aer_simulator')": 9400,
  "('realamprandom', 12, 'fake_fez')": 14650,
  "('realamprandom', 12, 'fake_kyiv')": 15350,
  "('realamprandom', 12, 'fake_marrakesh')": 14200,
  "('realamprandom', 12, 'fake_sherbrooke')": 15250,
  "('realamprandom', 12, 'fake_torino')": 14900,
  "('realamprandom', 13, 'aer_simulator')": 11750,
  "('realamprandom', 13, 'fake_fez')": 16900,
  "('realamprandom', 13, 'fake_kyiv')": 17150,
  "('realamprandom', 13, 'fake_marrakesh')": 16500,
  "('realamprandom', 13, 'fake_sherbrooke')": 17150,
  "('realamprandom', 13, 'fake_torino')": 17050,
  "('realamprandom', 14, 'aer_simulator')": 15200,
  "('realamprandom', 14, 'fake_fez')": 17650,
  "('realamprandom', 14, 'fake_kyiv')": 17700,
  "('realamprandom', 14, 'fake_marrakesh')": 17550,
  "('realamprandom', 14, 'fake_sherbrooke')": 17700,
  "('realamprandom', 14, 'fake_torino')": 17700,
  "('realamprandom', 15, 'aer_simulator')": 16250,
  "('realamprandom', 15, 'fake_fez')": 17900,
  "('realamprandom', 15, 'fake_kyiv')": 17900,
  "('realamprandom', 15, 'fake_marrakesh')": 17800,
  "('realamprandom', 15, 'fake_sherbrooke')": 17900,
  "('realamprandom', 15, 'fake_torino')": 17900,
  "('su2random', 4, 'aer_simulator')": 250,
  "('su2random', 4, 'fake_fez')": 250,
  "('su2random', 4, 'fake_kyiv')": 300,
  "('su2random', 4, 'fake_marrakesh')": 400,
  "('su2random', 4, 'fake_sherbrooke')": 400,
  "('su2random', 4, 'fake_torino')": 300,
  "('su2random', 5, 'aer_simulator')": 550,
  "('su2random', 5, 'fake_fez')": 450,
  "('su2random', 5, 'fake_kyiv')": 450,
  "('su2random', 5, 'fake_marrakesh')": 300,
  "('su2random', 5, 'fake_sherbrooke')": 350,
  "('su2random', 5, 'fake_torino')": 450,
  "('su2random', 6, 'aer_simulator')": 650,
  "('su2random', 6, 'fake_fez')": 1050,
  "('su2random', 6, 'fake_kyiv')": 1150,
  "('su2random', 6, 'fake_marrakesh')": 900,
  "('su2random', 6, 'fake_sherbrooke')": 800,
  "('su2random', 6, 'fake_torino')": 950,
  "('su2random', 7, 'aer_simulator')": 1600,
  "('su2random', 7, 'fake_fez')": 2050,
  "('su2random', 7, 'fake_kyiv')": 1750,
  "('su2random', 7, 'fake_marrakesh')": 1500,
  "('su2random', 7, 'fake_sherbrooke')": 1950,
  "('su2random', 7, 'fake_torino')": 1500,
  "('su2random', 8, 'aer_simulator')": 2550,
  "('su2random', 8, 'fake_fez')": 3450,
  "('su2random', 8, 'fake_kyiv')": 3050,
  "('su2random', 8, 'fake_marrakesh')": 3400,
  "('su2random', 8, 'fake_sherbrooke')": 3200,
  "('su2random', 8, 'fake_torino')": 3100,
  "('su2random', 9, 'aer_simulator')": 4250,
  "('su2random', 9, 'fake_fez')": 5400,
  "('su2random', 9, 'fake_kyiv')": 5900,
  "('su2random', 9, 'fake_marrakesh')": 5800,
  "('su2random', 9, 'fake_sherbrooke')": 5800,
  "('su2random', 9, 'fake_torino')": 5650,
  "('su2random', 10, 'aer_simulator')": 7150,
  "('su2random', 10, 'fake_fez')": 8700,
  "('su2random', 10, 'fake_kyiv')": 8650,
  "('su2random', 10, 'fake_marrakesh')": 8650,
  "('su2random', 10, 'fake_sherbrooke')": 9300,
  "('su2random', 10, 'fake_torino')": 8550,
  "('su2random', 11, 'aer_simulator')": 9850,
  "('su2random', 11, 'fake_fez')": 12350,
  "('su2random', 11, 'fake_kyiv')": 12400,
  "('su2random', 11, 'fake_marrakesh')": 12050,
  "('su2random', 11, 'fake_sherbrooke')": 12300,
  "('su2random', 11, 'fake_torino')": 12100,
  "('su2random', 12, 'aer_simulator')": 12950,
  "('su2random', 12, 'fake_fez')": 15250,
  "('su2random', 12, 'fake_kyiv')": 15250,
  "('su2random', 12, 'fake_marrakesh')": 15000,
  "('su2random', 12, 'fake_sherbrooke')": 15350,
  "('su2random', 12, 'fake_torino')": 15200,
  "('su2random', 13, 'aer_simulator')": 13700,
  "('su2random', 13, 'fake_fez')": 17000,
  "('su2random', 13, 'fake_kyiv')": 17250,
  "('su2random', 13, 'fake_marrakesh')": 16650,
  "('su2random', 13, 'fake_sherbrooke')": 17200,
  "('su2random', 13, 'fake_torino')": 17050,
  "('su2random', 14, 'aer_simulator')": 16350,
  "('su2random', 14, 'fake_fez')": 17700,
  "('su2random', 14, 'fake_kyiv')": 17700,
  "('su2random', 14, 'fake_marrakesh')": 17650,
  "('su2random', 14, 'fake_sherbrooke')": 17700,
  "('su2random', 14, 'fake_torino')": 17700,
  "('su2random', 15, 'aer_simulator')": 17050,
  "('su2random', 15, 'fake_fez')": 17900,
  "('su2random', 15, 'fake_kyiv')": 17900,
  "('su2random', 15, 'fake_marrakesh')": 17850,
  "('su2random', 15, 'fake_sherbrooke')": 17900,
  "('su2random', 15, 'fake_torino')": 17900,
  "('twolocalrandom', 4, 'aer_simulator')": 50,
  "('twolocalrandom', 4, 'fake_fez')": 150,
  "('twolocalrandom', 4, 'fake_kyiv')": 300,
  "('twolocalrandom', 4, 'fake_marrakesh')": 150,
  "('twolocalrandom', 4, 'fake_sherbrooke')": 150,
  "('twolocalrandom', 4, 'fake_torino')": 200,
  "('twolocalrandom', 5, 'aer_simulator')": 400,
  "('twolocalrandom', 5, 'fake_fez')": 400,
  "('twolocalrandom', 5, 'fake_kyiv')": 450,
  "('twolocalrandom', 5, 'fake_marrakesh')": 250,
  "('twolocalrandom', 5, 'fake_sherbrooke')": 400,
  "('twolocalrandom', 5, 'fake_torino')": 350,
  "('twolocalrandom', 6, 'aer_simulator')": 700,
  "('twolocalrandom', 6, 'fake_fez')": 950,
  "('twolocalrandom', 6, 'fake_kyiv')": 750,
  "('twolocalrandom', 6, 'fake_marrakesh')": 700,
  "('twolocalrandom', 6, 'fake_sherbrooke')": 1000,
  "('twolocalrandom', 6, 'fake_torino')": 1100,
  "('twolocalrandom', 7, 'aer_simulator')": 1250,
  "('twolocalrandom', 7, 'fake_fez')": 1550,
  "('twolocalrandom', 7, 'fake_kyiv')": 2050,
  "('twolocalrandom', 7, 'fake_marrakesh')": 1500,
  "('twolocalrandom', 7, 'fake_sherbrooke')": 1700,
  "('twolocalrandom', 7, 'fake_torino')": 2100,
  "('twolocalrandom', 8, 'aer_simulator')": 2050,
  "('twolocalrandom', 8, 'fake_fez')": 2550,
  "('twolocalrandom', 8, 'fake_kyiv')": 2950,
  "('twolocalrandom', 8, 'fake_marrakesh')": 3050,
  "('twolocalrandom', 8, 'fake_sherbrooke')": 3250,
  "('twolocalrandom', 8, 'fake_torino')": 3400,
  "('twolocalrandom', 9, 'aer_simulator')": 3250,
  "('twolocalrandom', 9, 'fake_fez')": 4800,
  "('twolocalrandom', 9, 'fake_kyiv')": 5550,
  "('twolocalrandom', 9, 'fake_marrakesh')": 5050,
  "('twolocalrandom', 9, 'fake_sherbrooke')": 5300,
  "('twolocalrandom', 9, 'fake_torino')": 5650,
  "('twolocalrandom', 10, 'aer_simulator')": 5200,
  "('twolocalrandom', 10, 'fake_fez')": 8350,
  "('twolocalrandom', 10, 'fake_kyiv')": 9100,
  "('twolocalrandom', 10, 'fake_marrakesh')": 8350,
  "('twolocalrandom', 10, 'fake_sherbrooke')": 8950,
  "('twolocalrandom', 10, 'fake_torino')": 8500,
  "('twolocalrandom', 11, 'aer_simulator')": 5250,
  "('twolocalrandom', 11, 'fake_fez')": 11850,
  "('twolocalrandom', 11, 'fake_kyiv')": 12050,
  "('twolocalrandom', 11, 'fake_marrakesh')": 11250,
  "('twolocalrandom', 11, 'fake_sherbrooke')": 12000,
  "('twolocalrandom', 11, 'fake_torino')": 11950,
  "('twolocalrandom', 12, 'aer_simulator')": 9200,
  "('twolocalrandom', 12, 'fake_fez')": 14900,
  "('twolocalrandom', 12, 'fake_kyiv')": 15000,
  "('twolocalrandom', 12, 'fake_marrakesh')": 14200,
  "('twolocalrandom', 12, 'fake_sherbrooke')": 15150,
  "('twolocalrandom', 12, 'fake_torino')": 14900,
  "('twolocalrandom', 13, 'aer_simulator')": 11900,
  "('twolocalrandom', 13, 'fake_fez')": 16950,
  "('twolocalrandom', 13, 'fake_kyiv')": 17200,
  "('twolocalrandom', 13, 'fake_marrakesh')": 16550,
  "('twolocalrandom', 13, 'fake_sherbrooke')": 17100,
  "('twolocalrandom', 13, 'fake_torino')": 16900,
  "('twolocalrandom', 14, 'aer_simulator')": 15050,
  "('twolocalrandom', 14, 'fake_fez')": 17650,
  "('twolocalrandom', 14, 'fake_kyiv')": 17700,
  "('twolocalrandom', 14, 'fake_marrakesh')": 17550,
  "('twolocalrandom', 14, 'fake_sherbrooke')": 17700,
  "('twolocalrandom', 14, 'fake_torino')": 17650,
  "('twolocalrandom', 15, 'aer_simulator')": 16300,
  "('twolocalrandom', 15, 'fake_fez')": 17850,
  "('twolocalrandom', 15, 'fake_kyiv')": 17900,
  "('twolocalrandom', 15, 'fake_marrakesh')": 17800,
  "('twolocalrandom', 15, 'fake_sherbrooke')": 17900,
  "('twolocalrandom', 15, 'fake_torino')": 17900,
  "('vqe', 4, 'aer_simulator')": 50,
  "('vqe', 4, 'fake_fez')": 50,
  "('vqe', 4, 'fake_kyiv')": 50,
  "('vqe', 4, 'fake_marrakesh')": 50,
  "('vqe', 4, 'fake_sherbrooke')": 50,
  "('vqe', 4, 'fake_torino')": 50,
  "('vqe', 5, 'aer_simulator')": 50,
  "('vqe', 5, 'fake_fez')": 50,
  "('vqe', 5, 'fake_kyiv')": 50,
  "('vqe', 5, 'fake_marrakesh')": 50,
  "('vqe', 5, 'fake_sherbrooke')": 50,
  "('vqe', 5, 'fake_torino')": 100,
  "('vqe', 6, 'aer_simulator')": 50,
  "('vqe', 6, 'fake_fez')": 50,
  "('vqe', 6, 'fake_marrakesh')": 50,
  "('vqe', 6, 'fake_sherbrooke')": 50,
  "('vqe', 6, 'fake_torino')": 50,
  "('vqe', 7, 'aer_simulator')": 50,
  "('vqe', 7, 'fake_fez')": 50,
  "('vqe', 7, 'fake_kyiv')": 100,
  "('vqe', 7, 'fake_marrakesh')": 100,
  "('vqe', 7, 'fake_sherbrooke')": 100,
  "('vqe', 7, 'fake_torino')": 150,
  "('vqe', 8, 'aer_simulator')": 100,
  "('vqe', 8, 'fake_fez')": 150,
  "('vqe', 8, 'fake_marrakesh')": 100,
  "('vqe', 8, 'fake_sherbrooke')": 300,
  "('vqe', 8, 'fake_torino')": 450,
  "('vqe', 9, 'aer_simulator')": 200,
  "('vqe', 9, 'fake_fez')": 150,
  "('vqe', 9, 'fake_kyiv')": 250,
  "('vqe', 9, 'fake_marrakesh')": 50,
  "('vqe', 9, 'fake_sherbrooke')": 350,
  "('vqe', 9, 'fake_torino')": 150,
  "('vqe', 10, 'aer_simulator')": 50,
  "('vqe', 10, 'fake_fez')": 200,
  "('vqe', 10, 'fake_kyiv')": 500,
  "('vqe', 10, 'fake_marrakesh')": 200,
  "('vqe', 10, 'fake_sherbrooke')": 600,
  "('vqe', 10, 'fake_torino')": 400,
  "('vqe', 11, 'aer_simulator')": 50,
  "('vqe', 11, 'fake_fez')": 150,
  "('vqe', 11, 'fake_kyiv')": 450,
  "('vqe', 11, 'fake_marrakesh')": 100,
  "('vqe', 11, 'fake_sherbrooke')": 300,
  "('vqe', 11, 'fake_torino')": 200,
  "('vqe', 12, 'aer_simulator')": 50,
  "('vqe', 12, 'fake_fez')": 300,
  "('vqe', 12, 'fake_marrakesh')": 150,
  "('vqe', 12, 'fake_sherbrooke')": 650,
  "('vqe', 12, 'fake_torino')": 350,
  "('vqe', 13, 'aer_simulator')": 150,
  "('vqe', 13, 'fake_fez')": 600,
  "('vqe', 13, 'fake_kyiv')": 1550,
  "('vqe', 13, 'fake_marrakesh')": 250,
  "('vqe', 13, 'fake_sherbrooke')": 1050,
  "('vqe', 13, 'fake_torino')": 1750,
  "('vqe', 14, 'aer_simulator')": 150,
  "('vqe', 14, 'fake_fez')": 1350,
  "('vqe', 14, 'fake_marrakesh')": 600,
  "('vqe', 14, 'fake_sherbrooke')": 2250,
  "('vqe', 14, 'fake_torino')": 2300,
  "('vqe', 15, 'aer_simulator')": 200,
  "('vqe', 15, 'fake_fez')": 1950,
  "('vqe', 15, 'fake_kyiv')": 2100,
  "('vqe', 15, 'fake_marrakesh')": 900,
  "('vqe', 15, 'fake_sherbrooke')": 3000,
  "('vqe', 15, 'fake_torino')": 2100,
  "('wstate', 4, 'aer_simulator')": 100,
  "('wstate', 4, 'fake_fez')": 150,
  "('wstate', 4, 'fake_kyiv')": 150,
  "('wstate', 4, 'fake_marrakesh')": 50,
  "('wstate', 4, 'fake_sherbrooke')": 250,
  "('wstate', 4, 'fake_torino')": 200,
  "('wstate', 5, 'aer_simulator')": 150,
  "('wstate', 5, 'fake_fez')": 150,
  "('wstate', 5, 'fake_kyiv')": 200,
  "('wstate', 5, 'fake_marrakesh')": 150,
  "('wstate', 5, 'fake_sherbrooke')": 200,
  "('wstate', 5, 'fake_torino')": 200,
  "('wstate', 6, 'aer_simulator')": 150,
  "('wstate', 6, 'fake_fez')": 100,
  "('wstate', 6, 'fake_kyiv')": 300,
  "('wstate', 6, 'fake_marrakesh')": 100,
  "('wstate', 6, 'fake_sherbrooke')": 400,
  "('wstate', 6, 'fake_torino')": 150,
  "('wstate', 7, 'aer_simulator')": 150,
  "('wstate', 7, 'fake_fez')": 450,
  "('wstate', 7, 'fake_kyiv')": 250,
  "('wstate', 7, 'fake_marrakesh')": 150,
  "('wstate', 7, 'fake_sherbrooke')": 400,
  "('wstate', 7, 'fake_torino')": 450,
  "('wstate', 8, 'aer_simulator')": 150,
  "('wstate', 8, 'fake_fez')": 300,
  "('wstate', 8, 'fake_kyiv')": 550,
  "('wstate', 8, 'fake_marrakesh')": 400,
  "('wstate', 8, 'fake_sherbrooke')": 600,
  "('wstate', 8, 'fake_torino')": 550,
  "('wstate', 9, 'aer_simulator')": 150,
  "('wstate', 9, 'fake_fez')": 400,
  "('wstate', 9, 'fake_kyiv')": 550,
  "('wstate', 9, 'fake_marrakesh')": 400,
  "('wstate', 9, 'fake_sherbrooke')": 700,
  "('wstate', 9, 'fake_torino')": 850,
  "('wstate', 10, 'aer_simulator')": 150,
  "('wstate', 10, 'fake_fez')": 600,
  "('wstate', 10, 'fake_kyiv')": 1000,
  "('wstate', 10, 'fake_marrakesh')": 500,
  "('wstate', 10, 'fake_sherbrooke')": 800,
  "('wstate', 10, 'fake_torino')": 700,
  "('wstate', 11, 'aer_simulator')": 200,
  "('wstate', 11, 'fake_fez')": 900,
  "('wstate', 11, 'fake_kyiv')": 1350,
  "('wstate', 11, 'fake_marrakesh')": 850,
  "('wstate', 11, 'fake_sherbrooke')": 1400,
  "('wstate', 11, 'fake_torino')": 1050,
  "('wstate', 12, 'aer_simulator')": 300,
  "('wstate', 12, 'fake_fez')": 800,
  "('wstate', 12, 'fake_kyiv')": 1650,
  "('wstate', 12, 'fake_marrakesh')": 900,
  "('wstate', 12, 'fake_sherbrooke')": 1900,
  "('wstate', 12, 'fake_torino')": 1350,
  "('wstate', 13, 'aer_simulator')": 200,
  "('wstate', 13, 'fake_fez')": 950,
  "('wstate', 13, 'fake_kyiv')": 2100,
  "('wstate', 13, 'fake_marrakesh')": 850,
  "('wstate', 13, 'fake_sherbrooke')": 2500,
  "('wstate', 13, 'fake_torino')": 1900,
  "('wstate', 14, 'aer_simulator')": 400,
  "('wstate', 14, 'fake_fez')": 900,
  "('wstate', 14, 'fake_kyiv')": 2800,
  "('wstate', 14, 'fake_marrakesh')": 1250,
  "('wstate', 14, 'fake_sherbrooke')": 2900,
  "('wstate', 14, 'fake_torino')": 2400,
  "('wstate', 15, 'aer_simulator')": 400,
  "('wstate', 15, 'fake_fez')": 1350,
  "('wstate', 15, 'fake_kyiv')": 3500,
  "('wstate', 15, 'fake_marrakesh')": 850,
  "('wstate', 15, 'fake_sherbrooke')": 2850,
  "('wstate', 15, 'fake_torino')": 2950,
  "('grover-noancilla', 4, 'aer_simulator')": 50,
  "('grover-noancilla', 4, 'fake_fez')": 300,
  "('grover-noancilla', 4, 'fake_kyiv')": 200,
  "('grover-noancilla', 4, 'fake_marrakesh')": 250,
  "('grover-noancilla', 4, 'fake_sherbrooke')": 150,
  "('grover-noancilla', 4, 'fake_torino')": 200,
  "('grover-noancilla', 5, 'aer_simulator')": 50,
  "('grover-noancilla', 5, 'fake_fez')": 500,
  "('grover-noancilla', 5, 'fake_kyiv')": 450,
  "('grover-noancilla', 5, 'fake_marrakesh')": 300,
  "('grover-noancilla', 5, 'fake_sherbrooke')": 350,
  "('grover-noancilla', 5, 'fake_torino')": 550,
  "('grover-noancilla', 6, 'aer_simulator')": 50,
  "('grover-noancilla', 6, 'fake_fez')": 800,
  "('grover-noancilla', 6, 'fake_kyiv')": 900,
  "('grover-noancilla', 6, 'fake_marrakesh')": 950,
  "('grover-noancilla', 6, 'fake_sherbrooke')": 650,
  "('grover-noancilla', 6, 'fake_torino')": 900,
  "('grover-noancilla', 7, 'aer_simulator')": 50,
  "('grover-noancilla', 7, 'fake_fez')": 1750,
  "('grover-noancilla', 7, 'fake_kyiv')": 2000,
  "('grover-noancilla', 7, 'fake_marrakesh')": 1850,
  "('grover-noancilla', 7, 'fake_sherbrooke')": 2100,
  "('grover-noancilla', 7, 'fake_torino')": 1800,
  "('grover-noancilla', 8, 'aer_simulator')": 50,
  "('grover-noancilla', 8, 'fake_fez')": 3550,
  "('grover-noancilla', 8, 'fake_kyiv')": 3500,
  "('grover-noancilla', 8, 'fake_marrakesh')": 3350,
  "('grover-noancilla', 8, 'fake_sherbrooke')": 3750,
  "('grover-noancilla', 8, 'fake_torino')": 3450,
  "('grover-noancilla', 9, 'aer_simulator')": 50,
  "('grover-noancilla', 9, 'fake_fez')": 5850,
  "('grover-noancilla', 9, 'fake_kyiv')": 6400,
  "('grover-noancilla', 9, 'fake_marrakesh')": 6000,
  "('grover-noancilla', 9, 'fake_sherbrooke')": 5600,
  "('grover-noancilla', 9, 'fake_torino')": 5600
}